flexible_neural_network_lib/__init__.py
flexible_neural_network_lib/flexible_network.py
flexible_neural_network_lib-0.1.0.dist-info/METADATA
flexible_neural_network_lib-0.1.0.dist-info/WHEEL
flexible_neural_network_lib-0.1.0.dist-info/top_level.txt
flexible_neural_network_lib-0.1.0.dist-info/RECORD
